gvtt/__init__.py
gvtt/config.py
gvtt/layers.py
gvtt/layers.yaml
gvtt/tech.py
gvtt/components/__init__.py
gvtt/components/bend_euler.py
gvtt/components/die.py
gvtt/components/edge_coupler_rib.py
gvtt/components/mmi1x2.py
gvtt/components/mmi2x2.py
gvtt/components/transitions.py
gvtt/klayout/layer_boolean.lym
gvtt/klayout/layers.lyp
gvtt/klayout/tech.lyt
gvtt-0.1.0.dist-info/LICENSE
gvtt-0.1.0.dist-info/WHEEL
gvtt-0.1.0.dist-info/METADATA
gvtt-0.1.0.dist-info/RECORD
