Metadata-Version: 2.1
Name: gvtt
Version: 0.1.0
Summary: gdsfactory VTT PDK
Keywords: python
Author-email: gdsfactory community <contact@gdsfactory.com>
Requires-Python: >=3.10
Classifier: Programming Language :: Python :: 3.10
Classifier: Programming Language :: Python :: 3.11
Classifier: Operating System :: OS Independent
Requires-Dist: gdsfactory~=8.4.0
Requires-Dist: pre-commit ; extra == "dev"
Requires-Dist: pytest ; extra == "dev"
Requires-Dist: pytest-cov ; extra == "dev"
Requires-Dist: pytest_regressions ; extra == "dev"
Requires-Dist: autodoc_pydantic ; extra == "docs"
Requires-Dist: jupytext ; extra == "docs"
Requires-Dist: jupyter-book>=0.15.1,<1.1 ; extra == "docs"
Provides-Extra: dev
Provides-Extra: docs
